rkt_ciutils/__init__.py
rkt_ciutils/boatci.py
rkt_ciutils/docker.py
rkt_ciutils/github.py
rkt_ciutils/tools.py
rkt_ciutils-3.0.4.dist-info/AUTHORS
rkt_ciutils-3.0.4.dist-info/METADATA
rkt_ciutils-3.0.4.dist-info/WHEEL
rkt_ciutils-3.0.4.dist-info/pbr.json
rkt_ciutils-3.0.4.dist-info/top_level.txt
rkt_ciutils-3.0.4.dist-info/RECORD
