Metadata-Version: 2.1
Name: rkt-ciutils
Version: 3.0.4
Summary: RiotKit Tools - Continuous Integration tools
Home-page: https://riotkit.org
Author: RiotKit non-profit organization
Author-email: riotkit@riseup.net
License: Apache-2
Keywords: docker,travis,ci,continuous-integration,devops
Platform: UNKNOWN
Classifier: Development Status :: 4 - Beta
Classifier: Environment :: Console
Classifier: Intended Audience :: Developers
Classifier: Intended Audience :: Information Technology
Classifier: License :: OSI Approved :: Apache Software License
Classifier: Operating System :: OS Independent
Classifier: Programming Language :: Python
Requires-Dist: rkd (<3,>=2.3.3)
Requires-Dist: requests (>=2.10)
